Metadata-Version: 2.1
Name: poptorch-model
Version: 0.0.2
Summary: poptorch pipeline model base class
Home-page: UNKNOWN
Author: Jinle Tong
Author-email: lancertong@live.com
License: MIT Licence
Keywords: pip,SICA,featureextraction
Platform: any
